fssucatools/__init__.py
fssucatools/fssucatools.py
fssucatools-0.1.2.dist-info/licenses/LICENSE
fssucatools-0.1.2.dist-info/METADATA
fssucatools-0.1.2.dist-info/WHEEL
fssucatools-0.1.2.dist-info/top_level.txt
fssucatools-0.1.2.dist-info/RECORD
