Metadata-Version: 2.4
Name: fssucatools
Version: 0.1.2
Summary: 简易录音工具模块，适合Tkinter教学使用
Author: 你的名字
Author-email: 307262079@qq.com
Classifier: Programming Language :: Python :: 3
Classifier: Operating System :: Microsoft :: Windows
Classifier: License :: OSI Approved :: MIT License
Classifier: Intended Audience :: Education
Classifier: Topic :: Multimedia :: Sound/Audio :: Capture/Recording
Requires-Python: >=3.10
License-File: LICENSE
Requires-Dist: numpy
Requires-Dist: sounddevice
Requires-Dist: scipy
Dynamic: author
Dynamic: author-email
Dynamic: classifier
Dynamic: description-content-type
Dynamic: license-file
Dynamic: requires-dist
Dynamic: requires-python
Dynamic: summary
